<?xml version="1.0" encoding="UTF-8" standalone="no" ?>
<!DOCTYPE rto SYSTEM "rto.dtd">
<rto>

  <text deck-line="-1" is-extract="false" line-id="-1" simulator="deckbuild" timestamp="1762971917" type="out">
*** this is deckbuild version 5.0.10.R ***

</text>

  <text deck-line="1" is-extract="false" line-id="1" simulator="" timestamp="1762971917" type="out"># TEST 1 
</text>

  <text deck-line="2" is-extract="false" line-id="2" simulator="" timestamp="1762971917" type="out">
</text>  <text deck-line="3" is-extract="false" line-id="3" simulator="" timestamp="1762971917" type="out"># Parameters Changed :: - 
</text>

  <text deck-line="4" is-extract="false" line-id="4" simulator="" timestamp="1762971917" type="out">
</text>  <text deck-line="5" is-extract="false" line-id="5" simulator="" timestamp="1762971917" type="out"># Total Design is new 
</text>

  <text deck-line="6" is-extract="false" line-id="6" simulator="" timestamp="1762971917" type="out"># ------------------------------------------------------------------------------------------------
</text>

  <text deck-line="7" is-extract="false" line-id="7" simulator="" timestamp="1762971917" type="out">
</text>  <text deck-line="8" is-extract="false" line-id="8" simulator="" timestamp="1762971917" type="out">
</text>  <text deck-line="9" is-extract="false" line-id="9" simulator="" timestamp="1762971917" type="out"># 10^-5 
</text>

  <text deck-line="10" is-extract="false" line-id="10" simulator="" timestamp="1762971917" type="out">#
</text>

  <text deck-line="11" is-extract="false" line-id="11" simulator="" timestamp="1762971917" type="out">#
</text>

  <text deck-line="12" is-extract="false" line-id="12" simulator="" timestamp="1762971917" type="out">#
</text>

  <text deck-line="13" is-extract="false" line-id="13" simulator="" timestamp="1762971917" type="out">#
</text>

  <text deck-line="14" is-extract="false" line-id="14" simulator="" timestamp="1762971917" type="out">
</text>  <text deck-line="15" is-extract="false" line-id="15" simulator="" timestamp="1762971917" type="out">
</text>  <text deck-line="16" is-extract="false" line-id="16" simulator="atlas" timestamp="1762971917" type="out">go atlas 
</text>

  <text deck-line="-1" is-extract="false" line-id="-1" simulator="atlas" timestamp="1762971917" type="out">

                                   A T L A S

            Version:  atlas 5.28.1.R (Wed Jun  5 11:14:46 PDT 2019)

                           Copyright (c) 1984 - 2019
                        Silvaco Inc. All rights reserved

    We acknowledge the contribution of the following collaborative partners:

                              Stanford University
</text>

  <text deck-line="-1" is-extract="false" line-id="-1" simulator="atlas" timestamp="1762971918" type="out">


               ======================================================

                  ATLAS                           : enabled

                  S-PISCES                        : enabled

                  BLAZE                           : enabled

                  GIGA                            : enabled

                  LUMINOUS                        : enabled

                  LED                             : enabled

                  TFT                             : en</text>

  <text deck-line="-1" is-extract="false" line-id="-1" simulator="atlas" timestamp="1762971918" type="out">abled

                  ORGANIC DISPLAY                 : enabled

                  ORGANIC SOLAR                   : enabled

                  MIXEDMODE                       : enabled

                  LASER                           : enabled

                  VCSEL                           : enabled

                  FERRO                           : enabled

                  QUANTUM                         : enabled

                  NOISE                           : enabled
</text>

  <text deck-line="-1" is-extract="false" line-id="-1" simulator="atlas" timestamp="1762971918" type="out">
                  REM                             : enabled

                  MAGNETIC                        : enabled

                  DEVICE3D                        : enabled

                  THERMAL3D                       : enabled

                  GIGA3D                          : enabled

                  MIXEDMODE3D                     : enabled

                  TFT3D                           : enabled

                  QUANTUM3D                       : enabled

     </text>

  <text deck-line="-1" is-extract="false" line-id="-1" simulator="atlas" timestamp="1762971918" type="out">             LUMINOUS3D                      : enabled

                  REM3D                           : enabled

                  MAGNETIC3D                      : enabled

                  LED3D                           : enabled

                  LASER3D                         : enabled

                  MIXEDMODE XL                    : enabled

                  S-PISCES BUNDLE                 : not licensed

                  BLAZE BUNDLE                    : not licensed

  </text>

  <text deck-line="-1" is-extract="false" line-id="-1" simulator="atlas" timestamp="1762971918" type="out">                TFT BUNDLE                      : not licensed

                  ORGANIC BUNDLE                  : not licensed

                  DEVICE3D BUNDLE                 : not licensed

                  TFT3D BUNDLE                    : not licensed

               ======================================================

                           Wed Nov 12 23:55:18 2025

                           Executing on host: VAIBHAV
                     Current SFLM Server: 127.0.0.1:3162/
</text>

  <text deck-line="-1" is-extract="false" line-id="-1" simulator="atlas" timestamp="1762971918" type="out">


ATLAS&gt; </text>

  <text deck-line="17" is-extract="false" line-id="17" simulator="atlas" timestamp="1762971918" type="out">
</text>  <text deck-line="-1" is-extract="false" line-id="-1" simulator="atlas" timestamp="1762971918" type="out">ATLAS&gt; </text>

  <text deck-line="18" is-extract="false" line-id="18" simulator="atlas" timestamp="1762971918" type="out">mesh THREE.D
</text>

  <text deck-line="-1" is-extract="false" line-id="-1" simulator="atlas" timestamp="1762971920" type="out">	####################################################
	######                                        ######
	######           Running on 1 CPU             ######
	######           12 CPUs available            ######
	######                                        ######
	####################################################
ATLAS&gt; </text>

  <text deck-line="19" is-extract="false" line-id="19" simulator="atlas" timestamp="1762971920" type="out">
</text>  <text deck-line="-1" is-extract="false" line-id="-1" simulator="atlas" timestamp="1762971920" type="out">ATLAS&gt; </text>

  <text deck-line="20" is-extract="false" line-id="20" simulator="atlas" timestamp="1762971920" type="out">x.mesh loc=0.00  spac=0.001
</text>

  <text deck-line="-1" is-extract="false" line-id="-1" simulator="atlas" timestamp="1762971920" type="out">ATLAS&gt; </text>

  <text deck-line="21" is-extract="false" line-id="21" simulator="atlas" timestamp="1762971920" type="out">x.mesh loc=0.0038  spac=0.001
</text>

  <text deck-line="-1" is-extract="false" line-id="-1" simulator="atlas" timestamp="1762971920" type="out">ATLAS&gt; </text>

  <text deck-line="22" is-extract="false" line-id="22" simulator="atlas" timestamp="1762971920" type="out">x.mesh loc=0.004  spac=0.001
</text>

  <text deck-line="-1" is-extract="false" line-id="-1" simulator="atlas" timestamp="1762971920" type="out">ATLAS&gt; </text>

  <text deck-line="23" is-extract="false" line-id="23" simulator="atlas" timestamp="1762971920" type="out">x.mesh loc=0.0058  spac=0.001
</text>

  <text deck-line="-1" is-extract="false" line-id="-1" simulator="atlas" timestamp="1762971920" type="out">ATLAS&gt; </text>

  <text deck-line="24" is-extract="false" line-id="24" simulator="atlas" timestamp="1762971920" type="out">x.mesh loc=0.006  spac=0.001
</text>

  <text deck-line="-1" is-extract="false" line-id="-1" simulator="atlas" timestamp="1762971920" type="out">ATLAS&gt; </text>

  <text deck-line="25" is-extract="false" line-id="25" simulator="atlas" timestamp="1762971920" type="out">x.mesh loc=0.011  spac=0.001
</text>

  <text deck-line="-1" is-extract="false" line-id="-1" simulator="atlas" timestamp="1762971920" type="out">ATLAS&gt; </text>

  <text deck-line="26" is-extract="false" line-id="26" simulator="atlas" timestamp="1762971920" type="out">x.mesh loc=0.0112  spac=0.001
</text>

  <text deck-line="-1" is-extract="false" line-id="-1" simulator="atlas" timestamp="1762971920" type="out">ATLAS&gt; </text>

  <text deck-line="27" is-extract="false" line-id="27" simulator="atlas" timestamp="1762971920" type="out">x.mesh loc=0.013  spac=0.001
</text>

  <text deck-line="-1" is-extract="false" line-id="-1" simulator="atlas" timestamp="1762971920" type="out">ATLAS&gt; </text>

  <text deck-line="28" is-extract="false" line-id="28" simulator="atlas" timestamp="1762971920" type="out">x.mesh loc=0.0132  spac=0.001
</text>

  <text deck-line="-1" is-extract="false" line-id="-1" simulator="atlas" timestamp="1762971920" type="out">ATLAS&gt; </text>

  <text deck-line="29" is-extract="false" line-id="29" simulator="atlas" timestamp="1762971920" type="out">x.mesh loc=0.017 spac=0.001
</text>

  <text deck-line="-1" is-extract="false" line-id="-1" simulator="atlas" timestamp="1762971920" type="out">ATLAS&gt; </text>

  <text deck-line="30" is-extract="false" line-id="30" simulator="atlas" timestamp="1762971920" type="out">
</text>  <text deck-line="-1" is-extract="false" line-id="-1" simulator="atlas" timestamp="1762971920" type="out">ATLAS&gt; </text>

  <text deck-line="31" is-extract="false" line-id="31" simulator="atlas" timestamp="1762971920" type="out">
</text>  <text deck-line="-1" is-extract="false" line-id="-1" simulator="atlas" timestamp="1762971920" type="out">ATLAS&gt; </text>

  <text deck-line="32" is-extract="false" line-id="32" simulator="atlas" timestamp="1762971920" type="out">y.mesh loc=0.00 spac=0.001
</text>

  <text deck-line="-1" is-extract="false" line-id="-1" simulator="atlas" timestamp="1762971920" type="out">ATLAS&gt; </text>

  <text deck-line="33" is-extract="false" line-id="33" simulator="atlas" timestamp="1762971920" type="out">y.mesh loc=0.005 spac=0.001
</text>

  <text deck-line="-1" is-extract="false" line-id="-1" simulator="atlas" timestamp="1762971920" type="out">ATLAS&gt; </text>

  <text deck-line="34" is-extract="false" line-id="34" simulator="atlas" timestamp="1762971920" type="out">y.mesh loc=0.008 spac=0.001
</text>

  <text deck-line="-1" is-extract="false" line-id="-1" simulator="atlas" timestamp="1762971920" type="out">ATLAS&gt; </text>

  <text deck-line="35" is-extract="false" line-id="35" simulator="atlas" timestamp="1762971920" type="out">y.mesh loc=0.013 spac=0.001
</text>

  <text deck-line="-1" is-extract="false" line-id="-1" simulator="atlas" timestamp="1762971920" type="out">ATLAS&gt; </text>

  <text deck-line="36" is-extract="false" line-id="36" simulator="atlas" timestamp="1762971920" type="out">y.mesh loc=0.0132 spac=0.001
</text>

  <text deck-line="-1" is-extract="false" line-id="-1" simulator="atlas" timestamp="1762971920" type="out">ATLAS&gt; </text>

  <text deck-line="37" is-extract="false" line-id="37" simulator="atlas" timestamp="1762971920" type="out">y.mesh loc=0.015 spac=0.001
</text>

  <text deck-line="-1" is-extract="false" line-id="-1" simulator="atlas" timestamp="1762971920" type="out">ATLAS&gt; </text>

  <text deck-line="38" is-extract="false" line-id="38" simulator="atlas" timestamp="1762971920" type="out">y.mesh loc=0.017 spac=0.001
</text>

  <text deck-line="-1" is-extract="false" line-id="-1" simulator="atlas" timestamp="1762971920" type="out">ATLAS&gt; </text>

  <text deck-line="39" is-extract="false" line-id="39" simulator="atlas" timestamp="1762971920" type="out">
</text>  <text deck-line="-1" is-extract="false" line-id="-1" simulator="atlas" timestamp="1762971920" type="out">ATLAS&gt; </text>

  <text deck-line="40" is-extract="false" line-id="40" simulator="atlas" timestamp="1762971920" type="out">
</text>  <text deck-line="-1" is-extract="false" line-id="-1" simulator="atlas" timestamp="1762971920" type="out">ATLAS&gt; </text>

  <text deck-line="41" is-extract="false" line-id="41" simulator="atlas" timestamp="1762971920" type="out">z.mesh loc = 0.00 spac=0.0005
</text>

  <text deck-line="-1" is-extract="false" line-id="-1" simulator="atlas" timestamp="1762971920" type="out">ATLAS&gt; </text>

  <text deck-line="42" is-extract="false" line-id="42" simulator="atlas" timestamp="1762971920" type="out">z.mesh loc = 0.017 spac=0.0005
</text>

  <text deck-line="-1" is-extract="false" line-id="-1" simulator="atlas" timestamp="1762971920" type="out">ATLAS&gt; </text>

  <text deck-line="43" is-extract="false" line-id="43" simulator="atlas" timestamp="1762971920" type="out">
</text>  <text deck-line="-1" is-extract="false" line-id="-1" simulator="atlas" timestamp="1762971920" type="out">ATLAS&gt; </text>

  <text deck-line="44" is-extract="false" line-id="44" simulator="atlas" timestamp="1762971920" type="out">#--------------------------------------------------------
</text>

  <text deck-line="-1" is-extract="false" line-id="-1" simulator="atlas" timestamp="1762971920" type="out">ATLAS&gt; </text>

  <text deck-line="45" is-extract="false" line-id="45" simulator="atlas" timestamp="1762971920" type="out">
</text>  <text deck-line="-1" is-extract="false" line-id="-1" simulator="atlas" timestamp="1762971920" type="out">ATLAS&gt; </text>

  <text deck-line="46" is-extract="false" line-id="46" simulator="atlas" timestamp="1762971920" type="out">region num=1 x.min=0.00 x.max=0.017 y.min=0.00 y.max=0.005 z.min=0.00 z.max=0.017  Silicon name=base
</text>

  <text deck-line="-1" is-extract="false" line-id="-1" simulator="atlas" timestamp="1762971920" type="out"> 
ATLAS&gt; </text>

  <text deck-line="47" is-extract="false" line-id="47" simulator="atlas" timestamp="1762971920" type="out">region num=2 x.min=0.00 x.max=0.017 y.min=0.005 y.max=0.008 z.min=0.00 z.max=0.017  oxide name=layer
</text>

  <text deck-line="-1" is-extract="false" line-id="-1" simulator="atlas" timestamp="1762971920" type="out">ATLAS&gt; </text>

  <text deck-line="48" is-extract="false" line-id="48" simulator="atlas" timestamp="1762971920" type="out">region num=3 x.min=0.006 x.max=0.011 y.min=0.008 y.max=0.013 z.min=0.00 z.max=0.017  Silicon name=channel
</text>

  <text deck-line="-1" is-extract="false" line-id="-1" simulator="atlas" timestamp="1762971920" type="out">ATLAS&gt; </text>

  <text deck-line="49" is-extract="false" line-id="49" simulator="atlas" timestamp="1762971920" type="out">
</text>  <text deck-line="-1" is-extract="false" line-id="-1" simulator="atlas" timestamp="1762971920" type="out">ATLAS&gt; </text>

  <text deck-line="50" is-extract="false" line-id="50" simulator="atlas" timestamp="1762971920" type="out">
</text>  <text deck-line="-1" is-extract="false" line-id="-1" simulator="atlas" timestamp="1762971920" type="out">ATLAS&gt; </text>

  <text deck-line="51" is-extract="false" line-id="51" simulator="atlas" timestamp="1762971920" type="out">#------ source / Drain separation -----------
</text>

  <text deck-line="-1" is-extract="false" line-id="-1" simulator="atlas" timestamp="1762971920" type="out">ATLAS&gt; </text>

  <text deck-line="52" is-extract="false" line-id="52" simulator="atlas" timestamp="1762971920" type="out">region num=4 x.min=0.006 x.max=0.011 y.min=0.008 y.max=0.013 z.min=0.00 z.max=0.005  Silicon name=sourceD
</text>

  <text deck-line="-1" is-extract="false" line-id="-1" simulator="atlas" timestamp="1762971920" type="out">ATLAS&gt; </text>

  <text deck-line="53" is-extract="false" line-id="53" simulator="atlas" timestamp="1762971920" type="out">region num=5 x.min=0.006 x.max=0.011 y.min=0.008 y.max=0.013 z.min=0.012 z.max=0.017  Silicon name=DrainD
</text>

  <text deck-line="-1" is-extract="false" line-id="-1" simulator="atlas" timestamp="1762971920" type="out">ATLAS&gt; </text>

  <text deck-line="54" is-extract="false" line-id="54" simulator="atlas" timestamp="1762971920" type="out">
</text>  <text deck-line="-1" is-extract="false" line-id="-1" simulator="atlas" timestamp="1762971920" type="out">ATLAS&gt; </text>

  <text deck-line="55" is-extract="false" line-id="55" simulator="atlas" timestamp="1762971920" type="out">
</text>  <text deck-line="-1" is-extract="false" line-id="-1" simulator="atlas" timestamp="1762971920" type="out">ATLAS&gt; </text>

  <text deck-line="56" is-extract="false" line-id="56" simulator="atlas" timestamp="1762971920" type="out"># -------- gate oxide ----------------
</text>

  <text deck-line="-1" is-extract="false" line-id="-1" simulator="atlas" timestamp="1762971920" type="out">ATLAS&gt; </text>

  <text deck-line="57" is-extract="false" line-id="57" simulator="atlas" timestamp="1762971920" type="out">region num=6 x.min=0.0058 x.max=0.006 y.min=0.008 y.max=0.013 z.min=0.006 z.max=0.011  material="hfo2" name=gate_oxide
</text>

  <text deck-line="-1" is-extract="false" line-id="-1" simulator="atlas" timestamp="1762971920" type="out">ATLAS&gt; </text>

  <text deck-line="58" is-extract="false" line-id="58" simulator="atlas" timestamp="1762971920" type="out">region num=6 x.min=0.0058 x.max=0.0112 y.min=0.013 y.max=0.0132 z.min=0.006 z.max=0.011  material="hfo2" name=gate_oxide
</text>

  <text deck-line="-1" is-extract="false" line-id="-1" simulator="atlas" timestamp="1762971920" type="out">ATLAS&gt; </text>

  <text deck-line="59" is-extract="false" line-id="59" simulator="atlas" timestamp="1762971920" type="out">region num=6 x.min=0.011 x.max=0.0112 y.min=0.008 y.max=0.013 z.min=0.006 z.max=0.011  material="hfo2" name=gate_oxide
</text>

  <text deck-line="-1" is-extract="false" line-id="-1" simulator="atlas" timestamp="1762971920" type="out">ATLAS&gt; </text>

  <text deck-line="60" is-extract="false" line-id="60" simulator="atlas" timestamp="1762971921" type="out">
</text>  <text deck-line="-1" is-extract="false" line-id="-1" simulator="atlas" timestamp="1762971921" type="out">ATLAS&gt; </text>

  <text deck-line="61" is-extract="false" line-id="61" simulator="atlas" timestamp="1762971921" type="out"># ---------- electrode ------------
</text>

  <text deck-line="-1" is-extract="false" line-id="-1" simulator="atlas" timestamp="1762971921" type="out">ATLAS&gt; </text>

  <text deck-line="62" is-extract="false" line-id="62" simulator="atlas" timestamp="1762971921" type="out">
</text>  <text deck-line="-1" is-extract="false" line-id="-1" simulator="atlas" timestamp="1762971921" type="out">ATLAS&gt; </text>

  <text deck-line="63" is-extract="false" line-id="63" simulator="atlas" timestamp="1762971921" type="out">#SOURCE
</text>

  <text deck-line="-1" is-extract="false" line-id="-1" simulator="atlas" timestamp="1762971921" type="out">ATLAS&gt; </text>

  <text deck-line="64" is-extract="false" line-id="64" simulator="atlas" timestamp="1762971921" type="out">electrode num=1 name=source x.min = 0.004 x.max = 0.006 y.min=0.008 y.max = 0.013 z.min=0.00 z.max=0.005 material=Aluminium
</text>

  <text deck-line="-1" is-extract="false" line-id="-1" simulator="atlas" timestamp="1762971921" type="out"> 
Electrode #1
Name: source              
 Number of boundary nodes: 264
 Dimensions in microns: 
       min         max
 x 4.000e-003  6.000e-003 
 y 8.000e-003  1.300e-002 
 z 0.000e+000  5.000e-003 

ATLAS&gt; </text>

  <text deck-line="65" is-extract="false" line-id="65" simulator="atlas" timestamp="1762971921" type="out">electrode num=1 name=source x.min = 0.004 x.max = 0.013 y.min=0.013 y.max = 0.015 z.min =0.00 z.max=0.005  material=Aluminium
</text>

  <text deck-line="-1" is-extract="false" line-id="-1" simulator="atlas" timestamp="1762971921" type="out"> 
Electrode #1
Name: source              
 Number of boundary nodes: 528
 Dimensions in microns: 
       min         max
 x 4.000e-003  1.300e-002 
 y 1.300e-002  1.500e-002 
 z 0.000e+000  5.000e-003 

ATLAS&gt; </text>

  <text deck-line="66" is-extract="false" line-id="66" simulator="atlas" timestamp="1762971921" type="out">electrode num=1 name=source x.min = 0.011 x.max = 0.013 y.min=0.008 y.max = 0.013 z.min =0.00 z.max=0.005 material=Aluminium
</text>

  <text deck-line="-1" is-extract="false" line-id="-1" simulator="atlas" timestamp="1762971921" type="out"> 
Electrode #1
Name: source              
 Number of boundary nodes: 264
 Dimensions in microns: 
       min         max
 x 1.100e-002  1.300e-002 
 y 8.000e-003  1.300e-002 
 z 0.000e+000  5.000e-003 

ATLAS&gt; </text>

  <text deck-line="67" is-extract="false" line-id="67" simulator="atlas" timestamp="1762971921" type="out">
</text>  <text deck-line="-1" is-extract="false" line-id="-1" simulator="atlas" timestamp="1762971921" type="out">ATLAS&gt; </text>

  <text deck-line="68" is-extract="false" line-id="68" simulator="atlas" timestamp="1762971921" type="out">
</text>  <text deck-line="-1" is-extract="false" line-id="-1" simulator="atlas" timestamp="1762971921" type="out">ATLAS&gt; </text>

  <text deck-line="69" is-extract="false" line-id="69" simulator="atlas" timestamp="1762971921" type="out">#drain
</text>

  <text deck-line="-1" is-extract="false" line-id="-1" simulator="atlas" timestamp="1762971921" type="out">ATLAS&gt; </text>

  <text deck-line="70" is-extract="false" line-id="70" simulator="atlas" timestamp="1762971921" type="out">electrode num=2 name=drain x.min = 0.004 x.max = 0.006 y.min=0.008 y.max = 0.013 z.min=0.012 z.max=0.017 material=Aluminium
</text>

  <text deck-line="-1" is-extract="false" line-id="-1" simulator="atlas" timestamp="1762971921" type="out"> 
Electrode #2
Name: drain               
 Number of boundary nodes: 264
 Dimensions in microns: 
       min         max
 x 4.000e-003  6.000e-003 
 y 8.000e-003  1.300e-002 
 z 1.200e-002  1.700e-002 

ATLAS&gt; </text>

  <text deck-line="71" is-extract="false" line-id="71" simulator="atlas" timestamp="1762971921" type="out">electrode num=2 name=drain x.min = 0.004 x.max = 0.013 y.min=0.013 y.max = 0.015 z.min =0.012 z.max=0.017  material=Aluminium
</text>

  <text deck-line="-1" is-extract="false" line-id="-1" simulator="atlas" timestamp="1762971921" type="out"> 
Electrode #2
Name: drain               
 Number of boundary nodes: 528
 Dimensions in microns: 
       min         max
 x 4.000e-003  1.300e-002 
 y 1.300e-002  1.500e-002 
 z 1.200e-002  1.700e-002 

ATLAS&gt; </text>

  <text deck-line="72" is-extract="false" line-id="72" simulator="atlas" timestamp="1762971921" type="out">electrode num=2 name=drain x.min = 0.011 x.max = 0.013 y.min=0.008 y.max = 0.013 z.min =0.012 z.max=0.017 material=Aluminium
</text>

  <text deck-line="-1" is-extract="false" line-id="-1" simulator="atlas" timestamp="1762971921" type="out"> 
Electrode #2
Name: drain               
 Number of boundary nodes: 264
 Dimensions in microns: 
       min         max
 x 1.100e-002  1.300e-002 
 y 8.000e-003  1.300e-002 
 z 1.200e-002  1.700e-002 

ATLAS&gt; </text>

  <text deck-line="73" is-extract="false" line-id="73" simulator="atlas" timestamp="1762971921" type="out">
</text>  <text deck-line="-1" is-extract="false" line-id="-1" simulator="atlas" timestamp="1762971921" type="out">ATLAS&gt; </text>

  <text deck-line="74" is-extract="false" line-id="74" simulator="atlas" timestamp="1762971921" type="out">#gate
</text>

  <text deck-line="-1" is-extract="false" line-id="-1" simulator="atlas" timestamp="1762971921" type="out">ATLAS&gt; </text>

  <text deck-line="75" is-extract="false" line-id="75" simulator="atlas" timestamp="1762971921" type="out">electrode num=3 x.min=0.0038 x.max=0.0058 y.min=0.008 y.max=0.0132 z.min=0.006 z.max=0.011  material=Aluminium name=gate
</text>

  <text deck-line="-1" is-extract="false" line-id="-1" simulator="atlas" timestamp="1762971921" type="out"> 
Electrode #3
Name: gate                
 Number of boundary nodes: 308
 Dimensions in microns: 
       min         max
 x 3.800e-003  5.800e-003 
 y 8.000e-003  1.320e-002 
 z 6.000e-003  1.100e-002 

ATLAS&gt; </text>

  <text deck-line="76" is-extract="false" line-id="76" simulator="atlas" timestamp="1762971921" type="out">electrode num=3 x.min=0.0038 x.max=0.0132 y.min=0.0132 y.max=0.0152 z.min=0.006 z.max=0.011 material=Aluminium name=gate
</text>

  <text deck-line="-1" is-extract="false" line-id="-1" simulator="atlas" timestamp="1762971921" type="out"> 
Electrode #3
Name: gate                
 Number of boundary nodes: 462
 Dimensions in microns: 
       min         max
 x 3.800e-003  1.320e-002 
 y 1.320e-002  1.500e-002 
 z 6.000e-003  1.100e-002 

Warning:  Electrode shortened in Y-direction.


ATLAS&gt; </text>

  <text deck-line="77" is-extract="false" line-id="77" simulator="atlas" timestamp="1762971921" type="out">electrode num=3 x.min=0.0112 x.max=0.0132 y.min=0.008 y.max=0.0132 z.min=0.006 z.max=0.011   material=Aluminium name=gate
</text>

  <text deck-line="-1" is-extract="false" line-id="-1" simulator="atlas" timestamp="1762971921" type="out"> 
Electrode #3
Name: gate                
 Number of boundary nodes: 308
 Dimensions in microns: 
       min         max
 x 1.120e-002  1.320e-002 
 y 8.000e-003  1.320e-002 
 z 6.000e-003  1.100e-002 

ATLAS&gt; </text>

  <text deck-line="78" is-extract="false" line-id="78" simulator="atlas" timestamp="1762971921" type="out">
</text>  <text deck-line="-1" is-extract="false" line-id="-1" simulator="atlas" timestamp="1762971921" type="out">ATLAS&gt; </text>

  <text deck-line="79" is-extract="false" line-id="79" simulator="atlas" timestamp="1762971921" type="out">#--------------------------------------------------
</text>

  <text deck-line="-1" is-extract="false" line-id="-1" simulator="atlas" timestamp="1762971921" type="out">ATLAS&gt; </text>

  <text deck-line="80" is-extract="false" line-id="80" simulator="atlas" timestamp="1762971921" type="out">
</text>  <text deck-line="-1" is-extract="false" line-id="-1" simulator="atlas" timestamp="1762971921" type="out">ATLAS&gt; </text>

  <text deck-line="81" is-extract="false" line-id="81" simulator="atlas" timestamp="1762971921" type="out">
</text>  <text deck-line="-1" is-extract="false" line-id="-1" simulator="atlas" timestamp="1762971921" type="out">ATLAS&gt; </text>

  <text deck-line="82" is-extract="false" line-id="82" simulator="atlas" timestamp="1762971921" type="out">#doping 
</text>

  <text deck-line="-1" is-extract="false" line-id="-1" simulator="atlas" timestamp="1762971921" type="out">ATLAS&gt; </text>

  <text deck-line="83" is-extract="false" line-id="83" simulator="atlas" timestamp="1762971921" type="out">doping uniform conc=1e17 p.type region =3
</text>

  <text deck-line="-1" is-extract="false" line-id="-1" simulator="atlas" timestamp="1762971921" type="out">
Mesh statistics:
 Total number of grid points    =   14630
 Number of grid points in plane =     418
 Number of triangles in plane   =     756
 Obtuse triangles in plane      =       0  ( 0.0%)
 Total number of z planes       =      35
 Total number of prisms         =   25704
</text>

  <text deck-line="-1" is-extract="false" line-id="-1" simulator="atlas" timestamp="1762971921" type="out">ATLAS&gt; </text>

  <text deck-line="84" is-extract="false" line-id="84" simulator="atlas" timestamp="1762971921" type="out">doping uniform conc=5e21 n.type region=4
</text>

  <text deck-line="-1" is-extract="false" line-id="-1" simulator="atlas" timestamp="1762971921" type="out">ATLAS&gt; </text>

  <text deck-line="85" is-extract="false" line-id="85" simulator="atlas" timestamp="1762971921" type="out">doping uniform conc=5e21 n.type region =5
</text>

  <text deck-line="-1" is-extract="false" line-id="-1" simulator="atlas" timestamp="1762971921" type="out">ATLAS&gt; </text>

  <text deck-line="86" is-extract="false" line-id="86" simulator="atlas" timestamp="1762971921" type="out">
</text>  <text deck-line="-1" is-extract="false" line-id="-1" simulator="atlas" timestamp="1762971921" type="out">ATLAS&gt; </text>

  <text deck-line="87" is-extract="false" line-id="87" simulator="atlas" timestamp="1762971921" type="out">#-------------------------------------------------
</text>

  <text deck-line="-1" is-extract="false" line-id="-1" simulator="atlas" timestamp="1762971921" type="out">ATLAS&gt; </text>

  <text deck-line="88" is-extract="false" line-id="88" simulator="atlas" timestamp="1762971921" type="out">
</text>  <text deck-line="-1" is-extract="false" line-id="-1" simulator="atlas" timestamp="1762971921" type="out">ATLAS&gt; </text>

  <text deck-line="89" is-extract="false" line-id="89" simulator="atlas" timestamp="1762971921" type="out">
</text>  <text deck-line="-1" is-extract="false" line-id="-1" simulator="atlas" timestamp="1762971921" type="out">ATLAS&gt; </text>

  <text deck-line="90" is-extract="false" line-id="90" simulator="atlas" timestamp="1762971921" type="out">#contact 
</text>

  <text deck-line="-1" is-extract="false" line-id="-1" simulator="atlas" timestamp="1762971921" type="out">ATLAS&gt; </text>

  <text deck-line="91" is-extract="false" line-id="91" simulator="atlas" timestamp="1762971921" type="out">
</text>  <text deck-line="-1" is-extract="false" line-id="-1" simulator="atlas" timestamp="1762971921" type="out">ATLAS&gt; </text>

  <text deck-line="92" is-extract="false" line-id="92" simulator="atlas" timestamp="1762971921" type="out">contact name = source workfun=4
</text>

  <text deck-line="-1" is-extract="false" line-id="-1" simulator="atlas" timestamp="1762971921" type="out"> Changing parameters for contact named source              .
ATLAS&gt; </text>

  <text deck-line="93" is-extract="false" line-id="93" simulator="atlas" timestamp="1762971921" type="out">contact name = drain workfun=4
</text>

  <text deck-line="-1" is-extract="false" line-id="-1" simulator="atlas" timestamp="1762971921" type="out"> Changing parameters for contact named drain               .
ATLAS&gt; </text>

  <text deck-line="94" is-extract="false" line-id="94" simulator="atlas" timestamp="1762971921" type="out">contact name = gate workfun=5
</text>

  <text deck-line="-1" is-extract="false" line-id="-1" simulator="atlas" timestamp="1762971921" type="out"> Changing parameters for contact named gate                .
ATLAS&gt; </text>

  <text deck-line="95" is-extract="false" line-id="95" simulator="atlas" timestamp="1762971921" type="out">
</text>  <text deck-line="-1" is-extract="false" line-id="-1" simulator="atlas" timestamp="1762971921" type="out">ATLAS&gt; </text>

  <text deck-line="96" is-extract="false" line-id="96" simulator="atlas" timestamp="1762971921" type="out"># -------------------------------------------
</text>

  <text deck-line="-1" is-extract="false" line-id="-1" simulator="atlas" timestamp="1762971921" type="out">ATLAS&gt; </text>

  <text deck-line="97" is-extract="false" line-id="97" simulator="atlas" timestamp="1762971922" type="out">
</text>  <text deck-line="-1" is-extract="false" line-id="-1" simulator="atlas" timestamp="1762971922" type="out">ATLAS&gt; </text>

  <text deck-line="98" is-extract="false" line-id="98" simulator="atlas" timestamp="1762971922" type="out">
</text>  <text deck-line="-1" is-extract="false" line-id="-1" simulator="atlas" timestamp="1762971922" type="out">ATLAS&gt; </text>

  <text deck-line="99" is-extract="false" line-id="99" simulator="atlas" timestamp="1762971922" type="out">
</text>  <text deck-line="-1" is-extract="false" line-id="-1" simulator="atlas" timestamp="1762971922" type="out">ATLAS&gt; </text>

  <text deck-line="100" is-extract="false" line-id="100" simulator="atlas" timestamp="1762971922" type="out">
</text>  <text deck-line="-1" is-extract="false" line-id="-1" simulator="atlas" timestamp="1762971922" type="out">ATLAS&gt; </text>

  <text deck-line="101" is-extract="false" line-id="101" simulator="atlas" timestamp="1762971922" type="out">
</text>  <text deck-line="-1" is-extract="false" line-id="-1" simulator="atlas" timestamp="1762971922" type="out">ATLAS&gt; </text>

  <text deck-line="102" is-extract="false" line-id="102" simulator="atlas" timestamp="1762971922" type="out">struct outfile= SiliconGate.str 
</text>

  <text deck-line="-1" is-extract="false" line-id="-1" simulator="atlas" timestamp="1762971922" type="out">  
 Warning: No Solution Present.
 Writing mesh only.

Starting module:   DEVICE 3D                      

</text>

  <text deck-line="-1" is-extract="false" line-id="-1" simulator="atlas" timestamp="1762971922" type="out">
MASTER format file written to SiliconGate.str
ATLAS&gt; </text>

  <text deck-line="-1" is-extract="false" line-id="103" simulator="atlas" timestamp="1762971922" type="out">tonyplot3d SiliconGate.str
</text>

  <text deck-line="104" is-extract="false" line-id="104" simulator="atlas" timestamp="1762971922" type="out">
</text>  <text deck-line="-1" is-extract="false" line-id="-1" simulator="atlas" timestamp="1762971922" type="out">ATLAS&gt; </text>

  <text deck-line="105" is-extract="false" line-id="105" simulator="atlas" timestamp="1762971922" type="out">
</text>  <text deck-line="-1" is-extract="false" line-id="-1" simulator="atlas" timestamp="1762971922" type="out">ATLAS&gt; </text>

  <text deck-line="106" is-extract="false" line-id="106" simulator="atlas" timestamp="1762971922" type="out">
</text>  <text deck-line="-1" is-extract="false" line-id="-1" simulator="atlas" timestamp="1762971922" type="out">ATLAS&gt; </text>

  <text deck-line="107" is-extract="false" line-id="107" simulator="atlas" timestamp="1762971922" type="out">models cvt srh auger  
</text>

  <text deck-line="-1" is-extract="false" line-id="-1" simulator="atlas" timestamp="1762971922" type="out">ATLAS&gt; </text>

  <text deck-line="108" is-extract="false" line-id="108" simulator="atlas" timestamp="1762971922" type="out">#
</text>

  <text deck-line="-1" is-extract="false" line-id="-1" simulator="atlas" timestamp="1762971922" type="out">ATLAS&gt; </text>

  <text deck-line="109" is-extract="false" line-id="109" simulator="atlas" timestamp="1762971922" type="out">mobility bn.cvt=4.75e7 bp.cvt=9.925e6 cn.cvt=1.74e5 cp.cvt=8.842e5 taun.cvt=0.125 taup.cvt=0.0317 gamn.cvt=2.5 gamp.cvt=2.2 mu0n.cvt=52.2 mu0p.cvt=44.9 mu1n.cvt=43.4 mu1p.cvt=29.0 mumaxn.cvt=1417.0 mumaxp.cvt=470.5 crn.cvt=9.68e16 crp.cvt=2.23e17 csn.cvt=3.43e20 csp.cvt=6.10e20 alphn.cvt=0.680 alphp.cvt=0.71 betan.cvt=2.0 betap.cvt=2.0 pcn.cvt=0.0 pcp.cvt=0.23e16 deln.cvt=5.82e14 delp.cvt=2.0546e14
</text>

  <text deck-line="-1" is-extract="false" line-id="-1" simulator="atlas" timestamp="1762971922" type="out">ATLAS&gt; </text>

  <text deck-line="110" is-extract="false" line-id="110" simulator="atlas" timestamp="1762971922" type="out">
</text>  <text deck-line="-1" is-extract="false" line-id="-1" simulator="atlas" timestamp="1762971922" type="out">ATLAS&gt; </text>

  <text deck-line="111" is-extract="false" line-id="111" simulator="atlas" timestamp="1762971922" type="out">
</text>  <text deck-line="-1" is-extract="false" line-id="-1" simulator="atlas" timestamp="1762971922" type="out">ATLAS&gt; </text>

  <text deck-line="112" is-extract="false" line-id="112" simulator="atlas" timestamp="1762971922" type="out">
</text>  <text deck-line="-1" is-extract="false" line-id="-1" simulator="atlas" timestamp="1762971922" type="out">ATLAS&gt; </text>

  <text deck-line="113" is-extract="false" line-id="113" simulator="atlas" timestamp="1762971922" type="out">method BICGST 
</text>

  <text deck-line="-1" is-extract="false" line-id="-1" simulator="atlas" timestamp="1762971922" type="out">ATLAS&gt; </text>

  <text deck-line="114" is-extract="false" line-id="114" simulator="atlas" timestamp="1762971922" type="out">solve init
</text>

  <text deck-line="-1" is-extract="false" line-id="-1" simulator="atlas" timestamp="1762971922" type="out">
Obtaining static solution:


init           psi    psi 
ICCG            x     rhs 
   i    j  m  -5.00* -26.0*
---------------------------
</text>

  <text deck-line="-1" is-extract="false" line-id="-1" simulator="atlas" timestamp="1762971923" type="out">   1       G   0.039 -18.64
</text>

  <text deck-line="-1" is-extract="false" line-id="-1" simulator="atlas" timestamp="1762971923" type="out">   2       G  -0.021 -18.68
</text>

  <text deck-line="-1" is-extract="false" line-id="-1" simulator="atlas" timestamp="1762971923" type="out">   3       G  -0.021 -18.73
</text>

  <text deck-line="-1" is-extract="false" line-id="-1" simulator="atlas" timestamp="1762971923" type="out">   4       G  -0.024 -18.78
</text>

  <text deck-line="-1" is-extract="false" line-id="-1" simulator="atlas" timestamp="1762971923" type="out">   5       G   0.588 -18.84
</text>

  <text deck-line="-1" is-extract="false" line-id="-1" simulator="atlas" timestamp="1762971924" type="out">   6       G   0.588 -18.91
</text>

  <text deck-line="-1" is-extract="false" line-id="-1" simulator="atlas" timestamp="1762971924" type="out">   7       G  -0.431 -18.99
</text>

  <text deck-line="-1" is-extract="false" line-id="-1" simulator="atlas" timestamp="1762971924" type="out">   8       G  -0.363 -19.09
</text>

  <text deck-line="-1" is-extract="false" line-id="-1" simulator="atlas" timestamp="1762971924" type="out">   9       G   0.166 -19.27
</text>

  <text deck-line="-1" is-extract="false" line-id="-1" simulator="atlas" timestamp="1762971924" type="out">  10       G  -0.410 -20.01
</text>

  <text deck-line="-1" is-extract="false" line-id="-1" simulator="atlas" timestamp="1762971924" type="out">  11       G  -2.395 -22.11
</text>

  <text deck-line="-1" is-extract="false" line-id="-1" simulator="atlas" timestamp="1762971924" type="out">  12       G  -6.18* -25.87
</text>

  <text deck-line="-1" is-extract="false" line-id="-1" simulator="atlas" timestamp="1762971925" type="out">ATLAS&gt; </text>

  <text deck-line="115" is-extract="false" line-id="115" simulator="atlas" timestamp="1762971925" type="out">solve vsource=0.0
</text>

  <text deck-line="-1" is-extract="false" line-id="-1" simulator="atlas" timestamp="1762971925" type="out">
Obtaining static solution:


prev           psi     n      p     psi     n      p  
BICGST          x      x      x     rhs    rhs    rhs 
   i    j  m  -5.00* -5.00* -5.00* -26.0* -17.3* -17.3*
-------------------------------------------------------
</text>

  <text deck-line="-1" is-extract="false" line-id="-1" simulator="atlas" timestamp="1762971926" type="out">   1       N  -6.98* -7.07* -7.89* -37.9* -23.1* -26.5*

Electrode       Va(V)        In(A)       Ip(A)       Ic(A)       It(A)
=========================================================================
source         0.000e+000 -1.494e-021 -2.860e-040 -1.494e-021 -1.494e-021
drain          0.000e+000 -2.490e-020  2.413e-041 -2.490e-020 -2.490e-020
gate           0.000e+000                          0.000e+000  0.000e+000
Total                                                         -2.639e-020

Tim</text>

  <text deck-line="-1" is-extract="false" line-id="-1" simulator="atlas" timestamp="1762971926" type="out">e for bias point:   1.00 sec. 
Total time:            7.00 sec. 
</text>

  <text deck-line="-1" is-extract="false" line-id="-1" simulator="atlas" timestamp="1762971926" type="out">ATLAS&gt; </text>

  <text deck-line="116" is-extract="false" line-id="116" simulator="atlas" timestamp="1762971926" type="out">solve vgate1=0.0 
</text>

  <text deck-line="-1" is-extract="false" line-id="-1" simulator="atlas" timestamp="1762971926" type="out">
Obtaining static solution:


prev           psi     n      p     psi     n      p  
BICGST          x      x      x     rhs    rhs    rhs 
   i    j  m  -5.00* -5.00* -5.00* -26.0* -17.3* -17.3*
-------------------------------------------------------
</text>

  <text deck-line="-1" is-extract="false" line-id="-1" simulator="atlas" timestamp="1762971927" type="out">   1       N  -12.1* -12.1* -11.4* -38.1* -23.1* -28.9*

Electrode       Va(V)        In(A)       Ip(A)       Ic(A)       It(A)
=========================================================================
source         0.000e+000  6.474e-021 -5.846e-042  6.474e-021  6.474e-021
drain          0.000e+000  3.187e-020 -8.084e-042  3.187e-020  3.187e-020
gate           0.000e+000                          0.000e+000  0.000e+000
Total                                                          3.834e-020

Tim</text>

  <text deck-line="-1" is-extract="false" line-id="-1" simulator="atlas" timestamp="1762971927" type="out">e for bias point:   1.00 sec. 
Total time:            8.00 sec. 
</text>

  <text deck-line="-1" is-extract="false" line-id="-1" simulator="atlas" timestamp="1762971927" type="out">ATLAS&gt; </text>

  <text deck-line="117" is-extract="false" line-id="117" simulator="atlas" timestamp="1762971927" type="out">
</text>  <text deck-line="-1" is-extract="false" line-id="-1" simulator="atlas" timestamp="1762971927" type="out">ATLAS&gt; </text>

  <text deck-line="118" is-extract="false" line-id="118" simulator="atlas" timestamp="1762971927" type="out">
</text>  <text deck-line="-1" is-extract="false" line-id="-1" simulator="atlas" timestamp="1762971927" type="out">ATLAS&gt; </text>

  <text deck-line="119" is-extract="false" line-id="119" simulator="atlas" timestamp="1762971927" type="out">
</text>  <text deck-line="-1" is-extract="false" line-id="-1" simulator="atlas" timestamp="1762971927" type="out">ATLAS&gt; </text>

  <text deck-line="120" is-extract="false" line-id="120" simulator="atlas" timestamp="1762971927" type="out">#solve vdrain=0.1
</text>

  <text deck-line="-1" is-extract="false" line-id="-1" simulator="atlas" timestamp="1762971927" type="out">ATLAS&gt; </text>

  <text deck-line="121" is-extract="false" line-id="121" simulator="atlas" timestamp="1762971927" type="out">solve vdrain=0.2
</text>

  <text deck-line="-1" is-extract="false" line-id="-1" simulator="atlas" timestamp="1762971927" type="out">
Obtaining static solution:

 V(  drain  ) = 0.2         


prev           psi     n      p     psi     n      p  
BICGST          x      x      x     rhs    rhs    rhs 
   i    j  m  -5.00* -5.00* -5.00* -26.0* -17.3* -17.3*
-------------------------------------------------------
</text>

  <text deck-line="-1" is-extract="false" line-id="-1" simulator="atlas" timestamp="1762971928" type="out">   1       N   1.622  1.049 -0.006 -24.44 -7.480 -16.38
</text>

  <text deck-line="-1" is-extract="false" line-id="-1" simulator="atlas" timestamp="1762971929" type="out">   2       N   3.384  1.755  2.047 -21.00 -6.588 -14.03
</text>

  <text deck-line="-1" is-extract="false" line-id="-1" simulator="atlas" timestamp="1762971930" type="out">   3       N   2.526  3.047  6.491 -21.76 -7.507 -8.566
</text>

  <text deck-line="-1" is-extract="false" line-id="-1" simulator="atlas" timestamp="1762971931" type="out">   4       N   3.024  4.589  9.346 -20.89 -7.739 -8.841

Warning: Solution diverging. Potential update too large.
 Update: 1057.19 Vstep: 7.73633


Warning: Convergence problem.  Taking smaller bias
step(s).  Bias step reduced 1 times.


Obtaining static solution:

 V(  drain  ) = 0.1         


prev           psi     n      p     psi     n      p  
BICGST          x      x      x     rhs    rhs    rhs 
   i    j  m  -5.00* -5.00* -5.00* -26.0* -17.3* -17.3*
------------------------------</text>

  <text deck-line="-1" is-extract="false" line-id="-1" simulator="atlas" timestamp="1762971931" type="out">-------------------------
</text>

  <text deck-line="-1" is-extract="false" line-id="-1" simulator="atlas" timestamp="1762971932" type="out">   1       N   1.036  0.525 -0.295 -25.11 -7.568 -17.15
</text>

  <text deck-line="-1" is-extract="false" line-id="-1" simulator="atlas" timestamp="1762971933" type="out">   2       N   1.230 -0.000 -0.126 -25.47 -7.964 -15.98
</text>

  <text deck-line="-1" is-extract="false" line-id="-1" simulator="atlas" timestamp="1762971934" type="out">   3       N   1.751  4.681 -0.022 -23.85 -7.468 -16.14
</text>

  <text deck-line="-1" is-extract="false" line-id="-1" simulator="atlas" timestamp="1762971935" type="out">   4       N   3.847  2.323  2.481 -20.63 -6.158 -13.73

Warning: Solution diverging. Potential update too large.
 Update: 7026.59 Vstep: 3.86817


Warning: Convergence problem.  Taking smaller bias
step(s).  Bias step reduced 2 times.

</text>

  <text deck-line="-1" is-extract="false" line-id="-1" simulator="atlas" timestamp="1762971935" type="out">
Obtaining static solution:

 V(  drain  ) = 0.05        


prev           psi     n      p     psi     n      p  
BICGST          x      x      x     rhs    rhs    rhs 
   i    j  m  -5.00* -5.00* -5.00* -26.0* -17.3* -17.3*
-------------------------------------------------------
</text>

  <text deck-line="-1" is-extract="false" line-id="-1" simulator="atlas" timestamp="1762971936" type="out">   1       N   0.501  0.068 -0.776 -27.4* -8.267 -18.2*
</text>

  <text deck-line="-1" is-extract="false" line-id="-1" simulator="atlas" timestamp="1762971936" type="out">   2       N   0.040  0.808 -1.217 -30.6* -9.198 -17.23
</text>

  <text deck-line="-1" is-extract="false" line-id="-1" simulator="atlas" timestamp="1762971937" type="out">   3       N  -0.793 -0.519 -1.712 -32.2* -10.79 -18.6*
</text>

  <text deck-line="-1" is-extract="false" line-id="-1" simulator="atlas" timestamp="1762971938" type="out">   4       N  -2.359 -2.037 -3.494 -33.3* -13.90 -20.4*
</text>

  <text deck-line="-1" is-extract="false" line-id="-1" simulator="atlas" timestamp="1762971938" type="out">   5       N  -5.44* -5.16* -5.31* -36.1* -20.1* -23.4*

Electrode       Va(V)        In(A)       Ip(A)       Ic(A)       It(A)
=========================================================================
source         0.000e+000 -1.644e-015  2.349e-030 -1.644e-015 -1.644e-015
drain          5.000e-002 -2.996e-015  2.687e-027 -2.996e-015 -2.996e-015
gate           0.000e+000                          0.000e+000  0.000e+000
Total                                                         -4.640e-015

Tim</text>

  <text deck-line="-1" is-extract="false" line-id="-1" simulator="atlas" timestamp="1762971938" type="out">e for bias point:   4.00 sec. 
Total time:           20.00 sec. 
</text>

  <text deck-line="-1" is-extract="false" line-id="-1" simulator="atlas" timestamp="1762971939" type="out">
Obtaining static solution:

 V(  drain  ) = 0.1         


proj           psi     n      p     psi     n      p  
BICGST          x      x      x     rhs    rhs    rhs 
   i    j  m  -5.00* -5.00* -5.00* -26.0* -17.3* -17.3*
-------------------------------------------------------
</text>

  <text deck-line="-1" is-extract="false" line-id="-1" simulator="atlas" timestamp="1762971940" type="out">   1       N  -0.980 -0.980 -2.962 -33.6* -14.42 -19.6*
</text>

  <text deck-line="-1" is-extract="false" line-id="-1" simulator="atlas" timestamp="1762971940" type="out">   2       N  -3.113 -2.610 -4.531 -36.9* -17.4* -23.6*

Electrode       Va(V)        In(A)       Ip(A)       Ic(A)       It(A)
=========================================================================
source         0.000e+000 -2.519e-015  4.696e-030 -2.519e-015 -2.519e-015
drain          1.000e-001  2.501e-015  3.075e-027  2.501e-015  2.501e-015
gate           0.000e+000                          0.000e+000  0.000e+000
Total                                                         -1.756e-017

Tim</text>

  <text deck-line="-1" is-extract="false" line-id="-1" simulator="atlas" timestamp="1762971940" type="out">e for bias point:   1.00 sec. 
Total time:           21.00 sec. 

Obtaining static solution:

 V(  drain  ) = 0.2         


proj           psi     n      p     psi     n      p  
BICGST          x      x      x     rhs    rhs    rhs 
   i    j  m  -5.00* -5.00* -5.00* -26.0* -17.3* -17.3*
-------------------------------------------------------
</text>

  <text deck-line="-1" is-extract="false" line-id="-1" simulator="atlas" timestamp="1762971941" type="out">   1       N  -0.551 -0.551 -2.560 -33.2* -13.10 -20.8*
</text>

  <text deck-line="-1" is-extract="false" line-id="-1" simulator="atlas" timestamp="1762971942" type="out">   2       N  -1.997 -1.771 -4.615 -35.2* -15.03 -22.8*
</text>

  <text deck-line="-1" is-extract="false" line-id="-1" simulator="atlas" timestamp="1762971943" type="out">   3       N  -4.588 -4.040 -6.94* -37.5* -19.5* -24.5*

Electrode       Va(V)        In(A)       Ip(A)       Ic(A)       It(A)
=========================================================================
source         0.000e+000 -4.511e-015  9.385e-030 -4.511e-015 -4.511e-015
drain          2.000e-001  4.511e-015  3.140e-027  4.511e-015  4.511e-015
gate           0.000e+000                          0.000e+000  0.000e+000
Total                                                          1.616e-019

Tim</text>

  <text deck-line="-1" is-extract="false" line-id="-1" simulator="atlas" timestamp="1762971943" type="out">e for bias point:   3.00 sec. 
Total time:           24.00 sec. 
</text>

  <text deck-line="-1" is-extract="false" line-id="-1" simulator="atlas" timestamp="1762971943" type="out">ATLAS&gt; </text>

  <text deck-line="122" is-extract="false" line-id="122" simulator="atlas" timestamp="1762971943" type="out">solve vdrain=0.4
</text>

  <text deck-line="-1" is-extract="false" line-id="-1" simulator="atlas" timestamp="1762971943" type="out">
Obtaining static solution:

 V(  drain  ) = 0.4         


proj           psi     n      p     psi     n      p  
BICGST          x      x      x     rhs    rhs    rhs 
   i    j  m  -5.00* -5.00* -5.00* -26.0* -17.3* -17.3*
-------------------------------------------------------
</text>

  <text deck-line="-1" is-extract="false" line-id="-1" simulator="atlas" timestamp="1762971944" type="out">   1       N  -0.238 -0.238 -2.229 -32.2* -12.13 -19.0*
</text>

  <text deck-line="-1" is-extract="false" line-id="-1" simulator="atlas" timestamp="1762971945" type="out">   2       N  -1.039 -1.013 -3.608 -35.1* -13.24 -21.6*
</text>

  <text deck-line="-1" is-extract="false" line-id="-1" simulator="atlas" timestamp="1762971945" type="out">   3       N  -2.648 -2.580 -5.40* -35.9* -15.84 -22.0*
</text>

  <text deck-line="-1" is-extract="false" line-id="-1" simulator="atlas" timestamp="1762971946" type="out">   4       N  -5.48* -5.34* -6.87* -37.8* -21.3* -24.</text>

  <text deck-line="-1" is-extract="false" line-id="-1" simulator="atlas" timestamp="1762971946" type="out">6*

Electrode       Va(V)        In(A)       Ip(A)       Ic(A)       It(A)
=========================================================================
source         0.000e+000 -1.222e-014  1.874</text>

  <text deck-line="-1" is-extract="false" line-id="-1" simulator="atlas" timestamp="1762971946" type="out">e-029 -1.222e-014 -1.222e-014
drain          4.000e-001  1.222e-014  3.143e-027  1.222e-014 </text>

  <text deck-line="-1" is-extract="false" line-id="-1" simulator="atlas" timestamp="1762971946" type="out"> 1.222e-014
gate           0.00</text>

  <text deck-line="-1" is-extract="false" line-id="-1" simulator="atlas" timestamp="1762971946" type="out">0e+000           </text>

  <text deck-line="-1" is-extract="false" line-id="-1" simulator="atlas" timestamp="1762971946" type="out">               0.000e+0</text>

  <text deck-line="-1" is-extract="false" line-id="-1" simulator="atlas" timestamp="1762971946" type="out">00</text>

  <text deck-line="-1" is-extract="false" line-id="-1" simulator="atlas" timestamp="1762971946" type="out">  0.000e+000</text>

  <text deck-line="-1" is-extract="false" line-id="-1" simulator="atlas" timestamp="1762971946" type="out">
Total                             </text>

  <text deck-line="-1" is-extract="false" line-id="-1" simulator="atlas" timestamp="1762971946" type="out">              </text>

  <text deck-line="-1" is-extract="false" line-id="-1" simulator="atlas" timestamp="1762971946" type="out">               1.3</text>

  <text deck-line="-1" is-extract="false" line-id="-1" simulator="atlas" timestamp="1762971946" type="out">30e-019

Time fo</text>

  <text deck-line="-1" is-extract="false" line-id="-1" simulator="atlas" timestamp="1762971946" type="out">r bias point:   3.0</text>

  <text deck-line="-1" is-extract="false" line-id="-1" simulator="atlas" timestamp="1762971946" type="out">0 sec. 
Total time:    </text>

  <text deck-line="-1" is-extract="false" line-id="-1" simulator="atlas" timestamp="1762971946" type="out">       27.00 sec. 
ATLAS&gt; </text>

  <text deck-line="123" is-extract="false" line-id="123" simulator="atlas" timestamp="1762971946" type="out">solve vdrain=0.6
</text>

  <text deck-line="-1" is-extract="false" line-id="-1" simulator="atlas" timestamp="1762971946" type="out">
Obtaining static solution:

 V(  drain  ) = 0.6         


proj           psi     n      p     psi     n      p  
BICGST          x      x      x     rhs    rhs    rhs 
   i    j  m  -5.00* -5.00* -5.00* -26.0* -17.3* -17.3*
-------------------------------------------------------
</text>

  <text deck-line="-1" is-extract="false" line-id="-1" simulator="atlas" timestamp="1762971947" type="out">   1       N  -0.401 -0.401 -2.401 -32.4* -12.13 -19.3*
</text>

  <text deck-line="-1" is-extract="false" line-id="-1" simulator="atlas" timestamp="1762971948" type="out">   2       N  -1.469 -1.404 -3.984 -34.1* -13.75 -20.8*
</text>

  <text deck-line="-1" is-extract="false" line-id="-1" simulator="atlas" timestamp="1762971948" type="out">   3       N  -3.512 -3.484 -4.982 -35.9* -17.30 -23.1*
</text>

  <text deck-line="-1" is-extract="false" line-id="-1" simulator="atlas" timestamp="1762971949" type="out">   4       N  -7.26* -7.19* -7.89* -38.0* -22.5* -26.1*

Electrode       Va(V)        In(A)       Ip(A)       Ic(A)       It(A)
=========================================================================
source         0.000e+000 -2.785e-014  2.807e-029 -2.785e-014 -2.785e-014
drain          6.000e-001  2.785e-014  3.146e-027  2.785e-014  2.785e-014
gate           0.000e+000                          0.000e+000  0.000e+000
Total                                                          1.994e-019

Tim</text>

  <text deck-line="-1" is-extract="false" line-id="-1" simulator="atlas" timestamp="1762971949" type="out">e for bias point:   3.00 sec. 
Total time:           30.00 sec. 
</text>

  <text deck-line="-1" is-extract="false" line-id="-1" simulator="atlas" timestamp="1762971949" type="out">ATLAS&gt; </text>

  <text deck-line="124" is-extract="false" line-id="124" simulator="atlas" timestamp="1762971949" type="out">solve vdrain=0.8
</text>

  <text deck-line="-1" is-extract="false" line-id="-1" simulator="atlas" timestamp="1762971949" type="out">
Obtaining static solution:

 V(  drain  ) = 0.8         


proj           psi     n      p     psi     n      p  
BICGST          x      x      x     rhs    rhs    rhs 
   i    j  m  -5.00* -5.00* -5.00* -26.0* -17.3* -17.3*
-------------------------------------------------------
</text>

  <text deck-line="-1" is-extract="false" line-id="-1" simulator="atlas" timestamp="1762971950" type="out">   1       N  -0.647 -0.647 -2.688 -32.2* -12.37 -19.3*
</text>

  <text deck-line="-1" is-extract="false" line-id="-1" simulator="atlas" timestamp="1762971951" type="out">   2       N  -2.012 -2.036 -4.112 -34.6* -14.66 -21.0*
</text>

  <text deck-line="-1" is-extract="false" line-id="-1" simulator="atlas" timestamp="1762971952" type="out">   3       N  -4.602 -4.506 -5.82* -37.3* -19.4* -24.1*

Electrode       Va(V)        In(A)       Ip(A)       Ic(A)       It(A)
=========================================================================
source         0.000e+000 -6.268e-014  3.737e-029 -6.268e-014 -6.268e-014
drain          8.000e-001  6.268e-014  3.150e-027  6.268e-014  6.268e-014
gate           0.000e+000                          0.000e+000  0.000e+000
Total                                                          4.376e-019

Tim</text>

  <text deck-line="-1" is-extract="false" line-id="-1" simulator="atlas" timestamp="1762971952" type="out">e for bias point:   3.00 sec. 
Total time:           33.00 sec. 
</text>

  <text deck-line="-1" is-extract="false" line-id="-1" simulator="atlas" timestamp="1762971952" type="out">ATLAS&gt; </text>

  <text deck-line="125" is-extract="false" line-id="125" simulator="atlas" timestamp="1762971952" type="out">
</text>  <text deck-line="-1" is-extract="false" line-id="-1" simulator="atlas" timestamp="1762971952" type="out">ATLAS&gt; </text>

  <text deck-line="126" is-extract="false" line-id="126" simulator="atlas" timestamp="1762971952" type="out">log outf=fin_trans_01.log
</text>

  <text deck-line="-1" is-extract="false" line-id="-1" simulator="atlas" timestamp="1762971952" type="out">ATLAS&gt; </text>

  <text deck-line="127" is-extract="false" line-id="127" simulator="atlas" timestamp="1762971952" type="out">#
</text>

  <text deck-line="-1" is-extract="false" line-id="-1" simulator="atlas" timestamp="1762971952" type="out">ATLAS&gt; </text>

  <text deck-line="128" is-extract="false" line-id="128" simulator="atlas" timestamp="1762971952" type="out">log outf= channel_5nm.log
</text>

  <text deck-line="-1" is-extract="false" line-id="-1" simulator="atlas" timestamp="1762971952" type="out">ATLAS&gt; </text>

  <text deck-line="129" is-extract="false" line-id="129" simulator="atlas" timestamp="1762971952" type="out">solve vgate=0.0 vstep=0.1 vfinal=1.0 name=gate
</text>

  <text deck-line="-1" is-extract="false" line-id="-1" simulator="atlas" timestamp="1762971952" type="out">
Obtaining static solution:


prev           psi     n      p     psi     n      p  
BICGST          x      x      x     rhs    rhs    rhs 
   i    j  m  -5.00* -5.00* -5.00* -26.0* -17.3* -17.3*
-------------------------------------------------------
</text>

  <text deck-line="-1" is-extract="false" line-id="-1" simulator="atlas" timestamp="1762971953" type="out">   1       N  -5.33* -6.00*  0.594 -37.9* -22.2* -20.6*

Electrode       Va(V)        In(A)       Ip(A)       Ic(A)       It(A)
=========================================================================
source         0.000e+000 -6.268e-014 -1.213e-026 -6.268e-014 -6.268e-014
drain          8.000e-001  6.268e-014  3.150e-027  6.268e-014  6.268e-014
gate           0.000e+000                          0.000e+000  0.000e+000
Total                                                          2.855e-019

Tim</text>

  <text deck-line="-1" is-extract="false" line-id="-1" simulator="atlas" timestamp="1762971953" type="out">e for bias point:   1.00 sec. 
Total time:           34.00 sec. 
</text>

  <text deck-line="-1" is-extract="false" line-id="-1" simulator="atlas" timestamp="1762971953" type="out">
Obtaining static solution:

 V(   gate  ) = 0.1         


prev           psi     n      p     psi     n      p  
BICGST          x      x      x     rhs    rhs    rhs 
   i    j  m  -5.00* -5.00* -5.00* -26.0* -17.3* -17.3*
-------------------------------------------------------
</text>

  <text deck-line="-1" is-extract="false" line-id="-1" simulator="atlas" timestamp="1762971954" type="out">   1       N   0.587  0.287 -0.301 -28.6* -11.47 -16.34
</text>

  <text deck-line="-1" is-extract="false" line-id="-1" simulator="atlas" timestamp="1762971955" type="out">   2       N  -1.537  0.227 -0.503 -34.4* -14.15 -20.1*
</text>

  <text deck-line="-1" is-extract="false" line-id="-1" simulator="atlas" timestamp="1762971956" type="out">   3       N  -3.864 -2.509 -4.302 -36.6* -18.0* -23.0*

Electrode       Va(V)        In(A)       Ip(A)       Ic(A)       It(A)
=========================================================================
source         0.000e+000 -7.676e-013 -2.830e-025 -7.676e-013 -7.676e-013
drain          8.000e-001  7.676e-013  3.149e-027  7.676e-013  7.676e-013
gate           1.000e-001                          0.000e+000  0.000e+000
Total                                                         -3.851e-018

Tim</text>

  <text deck-line="-1" is-extract="false" line-id="-1" simulator="atlas" timestamp="1762971956" type="out">e for bias point:   3.00 sec. 
Total time:           37.00 sec. 
</text>

  <text deck-line="-1" is-extract="false" line-id="-1" simulator="atlas" timestamp="1762971956" type="out">
Obtaining static solution:

 V(   gate  ) = 0.2         


proj           psi     n      p     psi     n      p  
BICGST          x      x      x     rhs    rhs    rhs 
   i    j  m  -5.00* -5.00* -5.00* -26.0* -17.3* -17.3*
-------------------------------------------------------
</text>

  <text deck-line="-1" is-extract="false" line-id="-1" simulator="atlas" timestamp="1762971957" type="out">   1       N  -1.079 -1.025 -2.541 -33.2* -13.11 -19.5*
</text>

  <text deck-line="-1" is-extract="false" line-id="-1" simulator="atlas" timestamp="1762971957" type="out">   2       N  -3.022 -2.744 -4.396 -35.7* -17.28 -23.0*
</text>

  <text deck-line="-1" is-extract="false" line-id="-1" simulator="atlas" timestamp="1762971958" type="out">   3       N  -6.89* -6.26* -7.33* -37.9* -22.1* -25.6*

Electrode       Va(V)        In(A)       Ip(A)       Ic(A)       It(A)
=========================================================================
source         0.000e+000 -9.400e-012 -6.473e-024 -9.400e-012 -9.400e-012
drain          8.000e-001  9.400e-012  3.147e-027  9.400e-012  9.400e-012
gate           2.000e-001                          0.000e+000  0.000e+000
Total                                                          6.683e-021

Tim</text>

  <text deck-line="-1" is-extract="false" line-id="-1" simulator="atlas" timestamp="1762971958" type="out">e for bias point:   2.00 sec. 
Total time:           39.00 sec. 
</text>

  <text deck-line="-1" is-extract="false" line-id="-1" simulator="atlas" timestamp="1762971958" type="out">
Obtaining static solution:

 V(   gate  ) = 0.3         


proj           psi     n      p     psi     n      p  
BICGST          x      x      x     rhs    rhs    rhs 
   i    j  m  -5.00* -5.00* -5.00* -26.0* -17.3* -17.3*
-------------------------------------------------------
</text>

  <text deck-line="-1" is-extract="false" line-id="-1" simulator="atlas" timestamp="1762971959" type="out">   1       N  -1.128 -1.128 -2.451 -34.0* -12.62 -20.4*
</text>

  <text deck-line="-1" is-extract="false" line-id="-1" simulator="atlas" timestamp="1762971960" type="out">   2       N  -3.065 -2.777 -4.553 -35.7* -16.53 -22.3*

Electrode       Va(V)        In(A)       Ip(A)       Ic(A)       It(A)
=========================================================================
source         0.000e+000 -1.147e-010 -1.469e-022 -1.147e-010 -1.147e-010
drain          8.000e-001  1.147e-010  3.145e-027  1.147e-010  1.147e-010
gate           3.000e-001                          0.000e+000  0.000e+000
Total                                                         -4.691e-016

Tim</text>

  <text deck-line="-1" is-extract="false" line-id="-1" simulator="atlas" timestamp="1762971960" type="out">e for bias point:   2.00 sec. 
Total time:           41.00 sec. 
</text>

  <text deck-line="-1" is-extract="false" line-id="-1" simulator="atlas" timestamp="1762971960" type="out">
Obtaining static solution:

 V(   gate  ) = 0.4         


proj           psi     n      p     psi     n      p  
BICGST          x      x      x     rhs    rhs    rhs 
   i    j  m  -5.00* -5.00* -5.00* -26.0* -17.3* -17.3*
-------------------------------------------------------
</text>

  <text deck-line="-1" is-extract="false" line-id="-1" simulator="atlas" timestamp="1762971961" type="out">   1       N  -1.076 -1.019 -2.351 -33.3* -12.35 -19.9*
</text>

  <text deck-line="-1" is-extract="false" line-id="-1" simulator="atlas" timestamp="1762971962" type="out">   2       N  -2.856 -2.416 -4.232 -35.3* -15.93 -21.1*
</text>

  <text deck-line="-1" is-extract="false" line-id="-1" simulator="atlas" timestamp="1762971963" type="out">   3       N  -6.60* -5.32* -1.491 -37.8* -21.7* -24.5*

Electrode       Va(V)        In(A)       Ip(A)       Ic(A)       It(A)
=========================================================================
source         0.000e+000 -1.326e-009 -3.225e-021 -1.326e-009 -1.326e-009
drain          8.000e-001  1.326e-009  3.144e-027  1.326e-009  1.326e-009
gate           4.000e-001                          0.000e+000  0.000e+000
Total                                                          8.728e-019

Tim</text>

  <text deck-line="-1" is-extract="false" line-id="-1" simulator="atlas" timestamp="1762971963" type="out">e for bias point:   3.00 sec. 
Total time:           44.00 sec. 
</text>

  <text deck-line="-1" is-extract="false" line-id="-1" simulator="atlas" timestamp="1762971963" type="out">
Obtaining static solution:

 V(   gate  ) = 0.5         


proj           psi     n      p     psi     n      p  
BICGST          x      x      x     rhs    rhs    rhs 
   i    j  m  -5.00* -5.00* -5.00* -26.0* -17.3* -17.3*
-------------------------------------------------------
</text>

  <text deck-line="-1" is-extract="false" line-id="-1" simulator="atlas" timestamp="1762971964" type="out">   1       N  -0.967 -0.487 -2.348 -33.2* -12.01 -20.0*
</text>

  <text deck-line="-1" is-extract="false" line-id="-1" simulator="atlas" timestamp="1762971964" type="out">   2       N  -2.593 -2.074 -4.038 -34.5* -15.36 -21.4*
</text>

  <text deck-line="-1" is-extract="false" line-id="-1" simulator="atlas" timestamp="1762971965" type="out">   3       N  -5.95* -4.595 -0.301 -30.6* -20.1* -21.7*

Electrode       Va(V)        In(A)       Ip(A)       Ic(A)       It(A)
=========================================================================
source         0.000e+000 -1.392e-008 -3.540e-020 -1.392e-008 -1.392e-008
drain          8.000e-001  1.392e-008  3.144e-027  1.392e-008  1.392e-008
gate           5.000e-001                          0.000e+000  0.000e+000
Total                                                          4.532e-017

Tim</text>

  <text deck-line="-1" is-extract="false" line-id="-1" simulator="atlas" timestamp="1762971965" type="out">e for bias point:   2.00 sec. 
Total time:           46.00 sec. 
</text>

  <text deck-line="-1" is-extract="false" line-id="-1" simulator="atlas" timestamp="1762971965" type="out">
Obtaining static solution:

 V(   gate  ) = 0.6         


proj           psi     n      p     psi     n      p  
BICGST          x      x      x     rhs    rhs    rhs 
   i    j  m  -5.00* -5.00* -5.00* -26.0* -17.3* -17.3*
-------------------------------------------------------
</text>

  <text deck-line="-1" is-extract="false" line-id="-1" simulator="atlas" timestamp="1762971966" type="out">   1       N  -0.800  0.166 -2.906 -33.1* -11.61 -20.5*
</text>

  <text deck-line="-1" is-extract="false" line-id="-1" simulator="atlas" timestamp="1762971967" type="out">   2       N  -2.288 -1.892 -4.104 -34.6* -14.55 -20.3*
</text>

  <text deck-line="-1" is-extract="false" line-id="-1" simulator="atlas" timestamp="1762971968" type="out">   3       N  -5.33* -4.017 -4.109 -37.1* -18.4* -23.8*

Electrode       Va(V)        In(A)       Ip(A)       Ic(A)       It(A)
=========================================================================
source         0.000e+000 -1.343e-007 -3.870e-019 -1.343e-007 -1.343e-007
drain          8.000e-001  1.343e-007  3.144e-027  1.343e-007  1.343e-007
gate           6.000e-001                          0.000e+000  0.000e+000
Total                                                          2.640e-015

Tim</text>

  <text deck-line="-1" is-extract="false" line-id="-1" simulator="atlas" timestamp="1762971968" type="out">e for bias point:   3.00 sec. 
Total time:           49.00 sec. 
</text>

  <text deck-line="-1" is-extract="false" line-id="-1" simulator="atlas" timestamp="1762971968" type="out">
Obtaining static solution:

 V(   gate  ) = 0.7         


proj           psi     n      p     psi     n      p  
BICGST          x      x      x     rhs    rhs    rhs 
   i    j  m  -5.00* -5.00* -5.00* -26.0* -17.3* -17.3*
-------------------------------------------------------
</text>

  <text deck-line="-1" is-extract="false" line-id="-1" simulator="atlas" timestamp="1762971969" type="out">   1       N  -0.392  0.247 -3.119 -32.7* -11.19 -20.5*
</text>

  <text deck-line="-1" is-extract="false" line-id="-1" simulator="atlas" timestamp="1762971969" type="out">   2       N  -1.306 -0.892 -3.663 -34.0* -12.35 -20.1*
</text>

  <text deck-line="-1" is-extract="false" line-id="-1" simulator="atlas" timestamp="1762971970" type="out">   3       N  -3.438 -2.631 -3.932 -35.3* -15.28 -22.0*
</text>

  <text deck-line="-1" is-extract="false" line-id="-1" simulator="atlas" timestamp="1762971971" type="out">   4       N  -6.07* -5.41* -1.656 -32.5* -19.2* -22.3*

Electrode       Va(V)        In(A)       Ip(A)       Ic(A)       It(A)
=========================================================================
source         0.000e+000 -9.490e-007 -2.097e-018 -9.490e-007 -9.490e-007
drain          8.000e-001  9.490e-007  3.145e-027  9.490e-007  9.490e-007
gate           7.000e-001                          0.000e+000  0.000e+000
Total                                                          3.348e-016

Tim</text>

  <text deck-line="-1" is-extract="false" line-id="-1" simulator="atlas" timestamp="1762971971" type="out">e for bias point:   3.00 sec. 
Total time:           52.00 sec. 
</text>

  <text deck-line="-1" is-extract="false" line-id="-1" simulator="atlas" timestamp="1762971971" type="out">
Obtaining static solution:

 V(   gate  ) = 0.8         


proj           psi     n      p     psi     n      p  
BICGST          x      x      x     rhs    rhs    rhs 
   i    j  m  -5.00* -5.00* -5.00* -26.0* -17.3* -17.3*
-------------------------------------------------------
</text>

  <text deck-line="-1" is-extract="false" line-id="-1" simulator="atlas" timestamp="1762971972" type="out">   1       N  -0.054 -0.010 -3.543 -32.4* -9.748 -20.0*
</text>

  <text deck-line="-1" is-extract="false" line-id="-1" simulator="atlas" timestamp="1762971972" type="out">   2       N  -0.547 -0.559 -3.878 -33.1* -10.57 -20.7*
</text>

  <text deck-line="-1" is-extract="false" line-id="-1" simulator="atlas" timestamp="1762971973" type="out">   3       N  -1.785 -1.451 -4.226 -34.7* -11.80 -22.2*
</text>

  <text deck-line="-1" is-extract="false" line-id="-1" simulator="atlas" timestamp="1762971973" type="out">   4       N  -3.357 -2.832 -4.502 -35.4* -14.26 -22.8*

Electrode       Va(V)        In(A)       Ip(A)       Ic(A)       It(A)
=========================================================================
source         0.000e+000 -4.678e-006 -1.007e-017 -4.678e-006 -4.678e-006
drain          8.000e-001  4.678e-006  3.153e-027  4.678e-006  4.678e-006
gate           8.000e-001                          0.000e+000  0.000e+000
Total                                                         -1.873e-012

Tim</text>

  <text deck-line="-1" is-extract="false" line-id="-1" simulator="atlas" timestamp="1762971973" type="out">e for bias point:   2.00 sec. 
Total time:           54.00 sec. 
</text>

  <text deck-line="-1" is-extract="false" line-id="-1" simulator="atlas" timestamp="1762971973" type="out">
Obtaining static solution:

 V(   gate  ) = 0.9         


proj           psi     n      p     psi     n      p  
BICGST          x      x      x     rhs    rhs    rhs 
   i    j  m  -5.00* -5.00* -5.00* -26.0* -17.3* -17.3*
-------------------------------------------------------
</text>

  <text deck-line="-1" is-extract="false" line-id="-1" simulator="atlas" timestamp="1762971975" type="out">   1       N   0.109  0.098 -3.235 -23.99 -8.771 -19.2*
</text>

  <text deck-line="-1" is-extract="false" line-id="-1" simulator="atlas" timestamp="1762971975" type="out">   2       N   0.833  2.579 -2.520 -23.27 -8.052 -18.5*
</text>

  <text deck-line="-1" is-extract="false" line-id="-1" simulator="atlas" timestamp="1762971976" type="out">   3       N   1.736  2.939 -0.944 -22.96 -7.720 -17.15
</text>

  <text deck-line="-1" is-extract="false" line-id="-1" simulator="atlas" timestamp="1762971977" type="out">   4       N   1.761  1.066 -1.245 -22.80 -7.883 -16.88

Warning: Solution diverging. Potential update too large.
 Update: 57.7108 Vstep: 3.86817


Warning: Convergence problem.  Taking smaller bias
step(s).  Bias step reduced 1 times.


Obtaining static solution:

 V(   gate  ) = 0.85        


proj           psi     n      p     psi     n      p  
BICGST          x      x      x     rhs    rhs    rhs 
   i    j  m  -5.00* -5.00* -5.00* -26.0* -17.3* -17.3*
------------------------------</text>

  <text deck-line="-1" is-extract="false" line-id="-1" simulator="atlas" timestamp="1762971977" type="out">-------------------------
</text>

  <text deck-line="-1" is-extract="false" line-id="-1" simulator="atlas" timestamp="1762971978" type="out">   1       N   0.024 -0.340 -3.702 -32.9* -9.911 -20.1*
</text>

  <text deck-line="-1" is-extract="false" line-id="-1" simulator="atlas" timestamp="1762971978" type="out">   2       N  -0.968 -0.689 -4.300 -33.4* -10.61 -20.8*
</text>

  <text deck-line="-1" is-extract="false" line-id="-1" simulator="atlas" timestamp="1762971979" type="out">   3       N  -1.795 -1.611 -4.369 -34.0* -12.20 -21.9*
</text>

  <text deck-line="-1" is-extract="false" line-id="-1" simulator="atlas" timestamp="1762971980" type="out">   4       N  -3.309 -3.266 -4.345 -35.7* -14.44 -22.4*

Electrode       Va(V)        In(A)       Ip(A)       Ic(A)       It(A)
=========================================================================
source         0.000e+000 -1.145e-005 -1.811e-017 -1.145e-005 -1.145e-005
drain          8.000e-001  1.145e-005  3.164e-027  1.145e-005  1.145e-005
gate           8.500e-001                          0.000e+000  0.000e+000
Total                                                          7.151e-012

Tim</text>

  <text deck-line="-1" is-extract="false" line-id="-1" simulator="atlas" timestamp="1762971980" type="out">e for bias point:   3.00 sec. 
Total time:            1.02 min. 
</text>

  <text deck-line="-1" is-extract="false" line-id="-1" simulator="atlas" timestamp="1762971980" type="out">
Obtaining static solution:

 V(   gate  ) = 0.9         


proj           psi     n      p     psi     n      p  
BICGST          x      x      x     rhs    rhs    rhs 
   i    j  m  -5.00* -5.00* -5.00* -26.0* -17.3* -17.3*
-------------------------------------------------------
</text>

  <text deck-line="-1" is-extract="false" line-id="-1" simulator="atlas" timestamp="1762971981" type="out">   1       N   0.081 -0.285 -3.980 -32.8* -9.365 -20.3*
</text>

  <text deck-line="-1" is-extract="false" line-id="-1" simulator="atlas" timestamp="1762971981" type="out">   2       N  -0.798 -0.339 -4.265 -32.3* -9.854 -21.1*
</text>

  <text deck-line="-1" is-extract="false" line-id="-1" simulator="atlas" timestamp="1762971982" type="out">   3       N  -1.048 -1.061 -4.091 -33.8* -10.67 -21.6*
</text>

  <text deck-line="-1" is-extract="false" line-id="-1" simulator="atlas" timestamp="1762971982" type="out">   4       N  -1.846 -1.687 -4.264 -34.2* -12.03 -22.1*
</text>

  <text deck-line="-1" is-extract="false" line-id="-1" simulator="atlas" timestamp="1762971983" type="out">   5       N  -3.322 -3.051 -3.971 -35.9* -13.74 -22.2*

Electrode       Va(V)        In(A)       Ip(A)       Ic(A)       It(A)
=========================================================================
source         0.000e+000 -2.754e-005 -2.123e-017 -2.754e-005 -2.754e-005
drain          8.000e-001  2.754e-005  3.190e-027  2.754e-005  2.754e-005
gate           9.000e-001                          0.000e+000  0.000e+000
Total                                                          6.662e-012

Tim</text>

  <text deck-line="-1" is-extract="false" line-id="-1" simulator="atlas" timestamp="1762971983" type="out">e for bias point:   3.00 sec. 
Total time:            1.07 min. 
</text>

  <text deck-line="-1" is-extract="false" line-id="-1" simulator="atlas" timestamp="1762971983" type="out">
Obtaining static solution:

 V(   gate  ) = 1           


proj           psi     n      p     psi     n      p  
BICGST          x      x      x     rhs    rhs    rhs 
   i    j  m  -5.00* -5.00* -5.00* -26.0* -17.3* -17.3*
-------------------------------------------------------
</text>

  <text deck-line="-1" is-extract="false" line-id="-1" simulator="atlas" timestamp="1762971985" type="out">   1       N   0.453 -0.000 -2.994 -23.07 -8.098 -18.9*
</text>

  <text deck-line="-1" is-extract="false" line-id="-1" simulator="atlas" timestamp="1762971986" type="out">   2       N   1.142  1.666 -3.561 -23.25 -7.897 -19.3*
</text>

  <text deck-line="-1" is-extract="false" line-id="-1" simulator="atlas" timestamp="1762971987" type="out">   3       N   1.184  2.160 -3.117 -23.06 -7.989 -19.2*
</text>

  <text deck-line="-1" is-extract="false" line-id="-1" simulator="atlas" timestamp="1762971988" type="out">   4       N   1.704  4.313 -1.860 -22.00 -7.433 -17.6*

Warning: Solution diverging. Potential update too large.
 Update: 50.5617 Vstep: 3.86817


Warning: Convergence problem.  Taking smaller bias
step(s).  Bias step reduced 1 times.


Obtaining static solution:

 V(   gate  ) = 0.95        


proj           psi     n      p     psi     n      p  
BICGST          x      x      x     rhs    rhs    rhs 
   i    j  m  -5.00* -5.00* -5.00* -26.0* -17.3* -17.3*
------------------------------</text>

  <text deck-line="-1" is-extract="false" line-id="-1" simulator="atlas" timestamp="1762971988" type="out">-------------------------
</text>

  <text deck-line="-1" is-extract="false" line-id="-1" simulator="atlas" timestamp="1762971989" type="out">   1       N  -0.092 -0.207 -3.423 -32.2* -9.350 -20.1*
</text>

  <text deck-line="-1" is-extract="false" line-id="-1" simulator="atlas" timestamp="1762971989" type="out">   2       N  -0.468 -0.672 -4.092 -33.5* -9.407 -21.0*
</text>

  <text deck-line="-1" is-extract="false" line-id="-1" simulator="atlas" timestamp="1762971990" type="out">   3       N   0.133  0.365 -4.028 -24.18 -8.656 -20.7*
</text>

  <text deck-line="-1" is-extract="false" line-id="-1" simulator="atlas" timestamp="1762971990" type="out">   4       N   0.298 -0.033 -3.380 -24.00 -8.616 -19.6*
</text>

  <text deck-line="-1" is-extract="false" line-id="-1" simulator="atlas" timestamp="1762971991" type="out">   5       N   0.302  0.804 -3.676 -23.83 -8.582 -19.6*
</text>

  <text deck-line="-1" is-extract="false" line-id="-1" simulator="atlas" timestamp="1762971992" type="out">   6       N   0.783  1.173 -3.566 -23.71 -7.781 -19.6*
</text>

  <text deck-line="-1" is-extract="false" line-id="-1" simulator="atlas" timestamp="1762971992" type="out">   7       N   0.913  2.070 -3.724 -23.20 -7.991 -19.7*
</text>

  <text deck-line="-1" is-extract="false" line-id="-1" simulator="atlas" timestamp="1762971993" type="out">   8       N   2.354  2.922 -1.221 -21.76 -6.864 -17.08

Warning: Solution diverging. Potential update too large.
 Update: 226.076 Vstep: 3.86817


Warning: Convergence problem.  Taking smaller bias
step(s).  Bias step reduced 2 times.


Obtaining static solution:

 V(   gate  ) = 0.925       


proj           psi     n      p     psi     n      p  
BICGST          x      x      x     rhs    rhs    rhs 
   i    j  m  -5.00* -5.00* -5.00* -26.0* -17.3* -17.3*
------------------------------</text>

  <text deck-line="-1" is-extract="false" line-id="-1" simulator="atlas" timestamp="1762971993" type="out">-------------------------
</text>

  <text deck-line="-1" is-extract="false" line-id="-1" simulator="atlas" timestamp="1762971994" type="out">   1       N   0.090  0.002 -3.807 -31.5* -8.831 -20.7*
</text>

  <text deck-line="-1" is-extract="false" line-id="-1" simulator="atlas" timestamp="1762971995" type="out">   2       N   0.390  0.391 -3.298 -23.99 -8.574 -19.5*
</text>

  <text deck-line="-1" is-extract="false" line-id="-1" simulator="atlas" timestamp="1762971996" type="out">   3       N   1.350  1.724 -2.546 -23.46 -7.541 -19.3*
</text>

  <text deck-line="-1" is-extract="false" line-id="-1" simulator="atlas" timestamp="1762971997" type="out">   4       N   2.553  2.343 -0.993 -22.13 -7.103 -16.86

Warning: Solution diverging. Potential update too large.
 Update: 357.274 Vstep: 3.86817


Warning: Convergence problem.  Taking smaller bias
step(s).  Bias step reduced 3 times.


Obtaining static solution:

 V(   gate  ) = 0.9125      


proj           psi     n      p     psi     n      p  
BICGST          x      x      x     rhs    rhs    rhs 
   i    j  m  -5.00* -5.00* -5.00* -26.0* -17.3* -17.3*
------------------------------</text>

  <text deck-line="-1" is-extract="false" line-id="-1" simulator="atlas" timestamp="1762971997" type="out">-------------------------
</text>

  <text deck-line="-1" is-extract="false" line-id="-1" simulator="atlas" timestamp="1762971997" type="out">   1       N  -0.720 -0.445 -4.164 -32.6* -9.195 -21.6*
</text>

  <text deck-line="-1" is-extract="false" line-id="-1" simulator="atlas" timestamp="1762971998" type="out">   2       N  -0.358 -0.348 -4.081 -33.4* -9.164 -21.4*
</text>

  <text deck-line="-1" is-extract="false" line-id="-1" simulator="atlas" timestamp="1762971999" type="out">   3       N   1.005  0.800 -3.378 -23.41 -8.039 -19.7*
</text>

  <text deck-line="-1" is-extract="false" line-id="-1" simulator="atlas" timestamp="1762971999" type="out">   4       N   2.802  2.905 -2.211 -21.66 -6.764 -18.9*

Warning: Solution diverging. Potential update too large.
 Update: 634.07 Vstep: 3.86817


Warning: Convergence problem.  Taking smaller bias
step(s).  Bias step reduced 4 times.


Obtaining static solution:

 V(   gate  ) = 0.90625     


proj           psi     n      p     psi     n      p  
BICGST          x      x      x     rhs    rhs    rhs 
   i    j  m  -5.00* -5.00* -5.00* -26.0* -17.3* -17.3*
-------------------------------</text>

  <text deck-line="-1" is-extract="false" line-id="-1" simulator="atlas" timestamp="1762971999" type="out">------------------------
</text>

  <text deck-line="-1" is-extract="false" line-id="-1" simulator="atlas" timestamp="1762972000" type="out">   1       N  -1.020 -0.974 -4.167 -33.4* -10.74 -21.8*
</text>

  <text deck-line="-1" is-extract="false" line-id="-1" simulator="atlas" timestamp="1762972001" type="out">   2       N  -2.016 -2.002 -4.294 -34.4* -12.35 -22.2*
</text>

  <text deck-line="-1" is-extract="false" line-id="-1" simulator="atlas" timestamp="1762972001" type="out">   3       N  -3.761 -3.447 -4.378 -35.9* -15.13 -22.2*

Electrode       Va(V)        In(A)       Ip(A)       Ic(A)       It(A)
=========================================================================
source         0.000e+000 -3.006e-005 -1.794e-017 -3.006e-005 -3.006e-005
drain          8.000e-001  3.006e-005  3.194e-027  3.006e-005  3.006e-005
gate           9.063e-001                          0.000e+000  0.000e+000
Total                                                          1.017e-011

Tim</text>

  <text deck-line="-1" is-extract="false" line-id="-1" simulator="atlas" timestamp="1762972001" type="out">e for bias point:   2.00 sec. 
Total time:            1.37 min. 
</text>

  <text deck-line="-1" is-extract="false" line-id="-1" simulator="atlas" timestamp="1762972001" type="out">
Obtaining static solution:

 V(   gate  ) = 0.9125      


proj           psi     n      p     psi     n      p  
BICGST          x      x      x     rhs    rhs    rhs 
   i    j  m  -5.00* -5.00* -5.00* -26.0* -17.3* -17.3*
-------------------------------------------------------
</text>

  <text deck-line="-1" is-extract="false" line-id="-1" simulator="atlas" timestamp="1762972002" type="out">   1       N  -1.514 -1.305 -4.400 -34.3* -11.60 -22.4*
</text>

  <text deck-line="-1" is-extract="false" line-id="-1" simulator="atlas" timestamp="1762972003" type="out">   2       N  -3.059 -2.840 -4.453 -35.3* -13.71 -22.3*

Electrode       Va(V)        In(A)       Ip(A)       Ic(A)       It(A)
=========================================================================
source         0.000e+000 -3.276e-005 -1.320e-017 -3.276e-005 -3.276e-005
drain          8.000e-001  3.276e-005  3.198e-027  3.276e-005  3.276e-005
gate           9.125e-001                          0.000e+000  0.000e+000
Total                                                          4.078e-011

Tim</text>

  <text deck-line="-1" is-extract="false" line-id="-1" simulator="atlas" timestamp="1762972003" type="out">e for bias point:   2.00 sec. 
Total time:            1.40 min. 
</text>

  <text deck-line="-1" is-extract="false" line-id="-1" simulator="atlas" timestamp="1762972003" type="out">
Obtaining static solution:

 V(   gate  ) = 0.925       


proj           psi     n      p     psi     n      p  
BICGST          x      x      x     rhs    rhs    rhs 
   i    j  m  -5.00* -5.00* -5.00* -26.0* -17.3* -17.3*
-------------------------------------------------------
</text>

  <text deck-line="-1" is-extract="false" line-id="-1" simulator="atlas" timestamp="1762972004" type="out">   1       N  -1.148 -0.793 -4.765 -33.0* -10.11 -22.4*
</text>

  <text deck-line="-1" is-extract="false" line-id="-1" simulator="atlas" timestamp="1762972004" type="out">   2       N  -1.812 -1.506 -4.792 -33.6* -11.34 -22.6*
</text>

  <text deck-line="-1" is-extract="false" line-id="-1" simulator="atlas" timestamp="1762972005" type="out">   3       N  -2.938 -2.551 -4.789 -35.2* -13.60 -22.7*

Electrode       Va(V)        In(A)       Ip(A)       Ic(A)       It(A)
=========================================================================
source         0.000e+000 -3.830e-005 -5.788e-018 -3.830e-005 -3.830e-005
drain          8.000e-001  3.830e-005  3.205e-027  3.830e-005  3.830e-005
gate           9.250e-001                          0.000e+000  0.000e+000
Total                                                          8.222e-011

Tim</text>

  <text deck-line="-1" is-extract="false" line-id="-1" simulator="atlas" timestamp="1762972005" type="out">e for bias point:   2.00 sec. 
Total time:            1.43 min. 
</text>

  <text deck-line="-1" is-extract="false" line-id="-1" simulator="atlas" timestamp="1762972005" type="out">
Obtaining static solution:

 V(   gate  ) = 0.95        


proj           psi     n      p     psi     n      p  
BICGST          x      x      x     rhs    rhs    rhs 
   i    j  m  -5.00* -5.00* -5.00* -26.0* -17.3* -17.3*
-------------------------------------------------------
</text>

  <text deck-line="-1" is-extract="false" line-id="-1" simulator="atlas" timestamp="1762972006" type="out">   1       N  -0.186 -0.404 -5.12* -33.3* -9.674 -22.2*
</text>

  <text deck-line="-1" is-extract="false" line-id="-1" simulator="atlas" timestamp="1762972007" type="out">   2       N  -1.023 -0.813 -5.50* -33.2* -10.32 -23.1*
</text>

  <text deck-line="-1" is-extract="false" line-id="-1" simulator="atlas" timestamp="1762972007" type="out">   3       N  -1.660 -1.445 -5.56* -34.6* -11.39 -23.5*
</text>

  <text deck-line="-1" is-extract="false" line-id="-1" simulator="atlas" timestamp="1762972008" type="out">   4       N  -2.714 -2.503 -5.59* -35.5* -13.56 -23.5*
</text>

  <text deck-line="-1" is-extract="false" line-id="-1" simulator="atlas" timestamp="1762972009" type="out">   5       N  -4.495 -4.572 -5.60* -36.6* -15.91 -23.6*

Electrode       Va(V)        In(A)       Ip(A)       Ic(A)       It(A)
=========================================================================
source         0.000e+000 -4.802e-005 -6.366e-019 -4.802e-005 -4.802e-005
drain          8.000e-001  4.802e-005  3.215e-027  4.802e-005  4.802e-005
gate           9.500e-001                          0.000e+000  0.000e+000
Total                                                          9.561e-013

Tim</text>

  <text deck-line="-1" is-extract="false" line-id="-1" simulator="atlas" timestamp="1762972009" type="out">e for bias point:   4.00 sec. 
Total time:            1.50 min. 
</text>

  <text deck-line="-1" is-extract="false" line-id="-1" simulator="atlas" timestamp="1762972009" type="out">
Obtaining static solution:

 V(   gate  ) = 1           


proj           psi     n      p     psi     n      p  
BICGST          x      x      x     rhs    rhs    rhs 
   i    j  m  -5.00* -5.00* -5.00* -26.0* -17.3* -17.3*
-------------------------------------------------------
</text>

  <text deck-line="-1" is-extract="false" line-id="-1" simulator="atlas" timestamp="1762972010" type="out">   1       N  -0.261 -0.391 -7.49* -31.8* -9.583 -24.5*
</text>

  <text deck-line="-1" is-extract="false" line-id="-1" simulator="atlas" timestamp="1762972010" type="out">   2       N  -0.838 -0.931 -7.62* -33.4* -10.57 -24.8*
</text>

  <text deck-line="-1" is-extract="false" line-id="-1" simulator="atlas" timestamp="1762972011" type="out">   3       N  -1.829 -1.840 -7.72* -34.3* -12.29 -25.4*
</text>

  <text deck-line="-1" is-extract="false" line-id="-1" simulator="atlas" timestamp="1762972011" type="out">   4       N  -3.528 -3.579 -7.64* -35.9* -14.42 -25.7*

Electrode       Va(V)        In(A)       Ip(A)       Ic(A)       It(A)
=========================================================================
source         0.000e+000 -6.420e-005 -3.567e-021 -6.420e-005 -6.420e-005
drain          8.000e-001  6.420e-005  3.229e-027  6.420e-005  6.420e-005
gate           1.000e+000                          0.000e+000  0.000e+000
Total                                                          2.551e-011

Tim</text>

  <text deck-line="-1" is-extract="false" line-id="-1" simulator="atlas" timestamp="1762972011" type="out">e for bias point:   2.00 sec. 
Total time:            1.53 min. 
</text>

  <text deck-line="-1" is-extract="false" line-id="-1" simulator="atlas" timestamp="1762972011" type="out">ATLAS&gt; </text>

  <text deck-line="-1" is-extract="false" line-id="130" simulator="atlas" timestamp="1762972011" type="out">tonyplot channel_5nm.log
</text>

  <text deck-line="131" is-extract="false" line-id="131" simulator="atlas" timestamp="1762972011" type="out">
</text>  <text deck-line="-1" is-extract="false" line-id="-1" simulator="atlas" timestamp="1762972011" type="out">ATLAS&gt; </text>

  <text deck-line="-1" is-extract="false" line-id="-1" simulator="EXTRACT" timestamp="1762972011" type="out">EXTRACT&gt; </text>

  <text deck-line="-1" is-extract="false" line-id="-1" simulator="EXTRACT" timestamp="1762972011" type="out">extract name="vt" (xintercept(maxslope(curve(abs(v."gate"),abs(i."drain")))) - abs(ave(v."drain"))/2.0)
</text>

  <text deck-line="-1" is-extract="false" line-id="-1" simulator="EXTRACT" timestamp="1762972012" type="err">ERROR : Initialization has not been performed.
</text>

  <text deck-line="133" is-extract="false" line-id="133" simulator="atlas" timestamp="1762972012" type="out">
</text>  <text deck-line="-1" is-extract="false" line-id="-1" simulator="atlas" timestamp="1762972012" type="out">ATLAS&gt; </text>

  <text deck-line="-1" is-extract="false" line-id="-1" simulator="extract" timestamp="1762972012" type="out">
</text>  <text deck-line="-1" is-extract="false" line-id="-1" simulator="EXTRACT" timestamp="1762972012" type="out">EXTRACT&gt; # Proceed with saving the structure and other outputs
</text>

  <text deck-line="-1" is-extract="false" line-id="-1" simulator="EXTRACT" timestamp="1762972012" type="out">EXTRACT&gt; </text>

  <text deck-line="-1" is-extract="false" line-id="-1" simulator="EXTRACT" timestamp="1762972012" type="out">quit
</text>

  <text deck-line="135" is-extract="false" line-id="135" simulator="atlas" timestamp="1762972012" type="out">log outf=siliconComp4_8.str
</text>

  <text deck-line="-1" is-extract="false" line-id="-1" simulator="atlas" timestamp="1762972012" type="out">ATLAS&gt; </text>

  <text deck-line="136" is-extract="false" line-id="136" simulator="atlas" timestamp="1762972012" type="out">output j.electron j.hole j.conduc j.total ex.field ey.field flowlines e.mobility h.mobility e.temp h.temp con.band val.band qfn j.disp photogen impact 
</text>

  <text deck-line="-1" is-extract="false" line-id="-1" simulator="atlas" timestamp="1762972012" type="out">ATLAS&gt; </text>

  <text deck-line="137" is-extract="false" line-id="137" simulator="atlas" timestamp="1762972012" type="out">save outf=siliconComp4_8.str
</text>

  <text deck-line="-1" is-extract="false" line-id="-1" simulator="atlas" timestamp="1762972014" type="out">
MASTER format file written to siliconComp4_8.str
</text>

  <text deck-line="-1" is-extract="false" line-id="-1" simulator="atlas" timestamp="1762972014" type="out">ATLAS&gt; </text>

  <text deck-line="138" is-extract="false" line-id="138" simulator="atlas" timestamp="1762972014" type="out">
</text>  <text deck-line="-1" is-extract="false" line-id="-1" simulator="atlas" timestamp="1762972014" type="out">ATLAS&gt; </text>

  <text deck-line="139" is-extract="false" line-id="139" simulator="atlas" timestamp="1762972014" type="out">struct outfile=siliconComp4_8.str
</text>

  <text deck-line="-1" is-extract="false" line-id="-1" simulator="atlas" timestamp="1762972016" type="out">
MASTER format file written to siliconComp4_8.str
</text>

  <text deck-line="-1" is-extract="false" line-id="-1" simulator="atlas" timestamp="1762972016" type="out">ATLAS&gt; </text>

  <text deck-line="-1" is-extract="false" line-id="140" simulator="atlas" timestamp="1762972016" type="out">tonyplot3d siliconComp4_8.str
</text>

  <text deck-line="141" is-extract="false" line-id="141" simulator="atlas" timestamp="1762972016" type="out">quit
</text>

  <text deck-line="-1" is-extract="false" line-id="-1" simulator="atlas" timestamp="1762972016" type="out">
ATLAS version 5.28.1.R finished at Wed Nov 12 23:56:56 2025
</text>

</rto>
